{
  "color": "#c63939",
  "generations": [
    ["Hololive EN", "Justice"]
  ],
  "id": "5b7d09W6RvGKZVn0K5ZIPY",
  "name": "Elizabeth Rose Bloodflame",
  "stats": {
    "2024-06-25": {"followers": 189, "monthlyListeners": 986},
    "2024-06-26": {"followers": 684, "monthlyListeners": 5768},
    "2024-06-29": {"followers": 944, "monthlyListeners": 8576},
    "2024-07-02": {"followers": 1096, "monthlyListeners": 10169},
    "2024-07-08": {"followers": 1348, "monthlyListeners": 14369},
    "2024-07-11": {"followers": 1437, "monthlyListeners": 17710},
    "2024-07-14": {"followers": 1527, "monthlyListeners": 19779},
    "2024-07-17": {"followers": 1620, "monthlyListeners": 23568},
    "2024-07-20": {"followers": 1685, "monthlyListeners": 25906},
    "2024-07-23": {"followers": 1749, "monthlyListeners": 26990},
    "2024-07-26": {"followers": 1830, "monthlyListeners": 28000},
    "2024-07-29": {"followers": 1870, "monthlyListeners": 28112},
    "2024-08-01": {"followers": 1919, "monthlyListeners": 28540},
    "2024-08-04": {"followers": 1974, "monthlyListeners": 28048},
    "2024-08-07": {"followers": 2028, "monthlyListeners": 27071},
    "2024-08-13": {"followers": 2149, "monthlyListeners": 25124},
    "2024-08-16": {"followers": 2195, "monthlyListeners": 24588},
    "2024-08-28": {"followers": 2359, "monthlyListeners": 22678},
    "2024-08-31": {"followers": 2409, "monthlyListeners": 22644},
    "2024-09-03": {"followers": 2481, "monthlyListeners": 24551},
    "2024-09-06": {"followers": 2545, "monthlyListeners": 25991},
    "2024-09-09": {"followers": 2643, "monthlyListeners": 34605},
    "2024-09-12": {"followers": 2769, "monthlyListeners": 39140},
    "2024-09-15": {"followers": 2847, "monthlyListeners": 42560},
    "2024-09-18": {"followers": 2903, "monthlyListeners": 44841},
    "2024-09-21": {"followers": 2962, "monthlyListeners": 47331},
    "2024-09-24": {"followers": 3015, "monthlyListeners": 49062},
    "2024-09-27": {"followers": 3066, "monthlyListeners": 50432},
    "2024-09-30": {"followers": 3126, "monthlyListeners": 51055},
    "2024-10-03": {"followers": 3191, "monthlyListeners": 49900},
    "2024-10-06": {"followers": 3253, "monthlyListeners": 45315},
    "2024-10-09": {"followers": 3308, "monthlyListeners": 42016},
    "2024-10-12": {"followers": 3379, "monthlyListeners": 39138},
    "2024-10-15": {"followers": 3437, "monthlyListeners": 38199},
    "2024-10-18": {"followers": 3487, "monthlyListeners": 35910},
    "2024-10-21": {"followers": 3565, "monthlyListeners": 34453},
    "2024-10-24": {"followers": 3629, "monthlyListeners": 33366},
    "2024-10-27": {"followers": 3761, "monthlyListeners": 32151},
    "2024-10-30": {"followers": 5210, "monthlyListeners": 32359},
    "2024-11-02": {"followers": 6884, "monthlyListeners": 36683},
    "2024-11-05": {"followers": 7469, "monthlyListeners": 37943},
    "2024-11-08": {"followers": 7973, "monthlyListeners": 38821},
    "2024-11-11": {"followers": 8312, "monthlyListeners": 39210},
    "2024-11-14": {"followers": 8699, "monthlyListeners": 40419},
    "2024-11-17": {"followers": 9137, "monthlyListeners": 41576},
    "2024-11-20": {"followers": 9432, "monthlyListeners": 42502},
    "2024-11-23": {"followers": 9670, "monthlyListeners": 43571},
    "2024-11-26": {"followers": 9925, "monthlyListeners": 44759},
    "2024-11-29": {"followers": 10181, "monthlyListeners": 44007},
    "2024-12-02": {"followers": 10527, "monthlyListeners": 43164},
    "2024-12-05": {"followers": 10820, "monthlyListeners": 43135},
    "2024-12-08": {"followers": 11111, "monthlyListeners": 43024},
    "2024-12-11": {"followers": 11843, "monthlyListeners": 43859},
    "2024-12-14": {"followers": 12677, "monthlyListeners": 44659},
    "2024-12-17": {"followers": 13068, "monthlyListeners": 46129},
    "2024-12-20": {"followers": 13382, "monthlyListeners": 47902},
    "2024-12-23": {"followers": 13662, "monthlyListeners": 49019},
    "2024-12-26": {"followers": 13924, "monthlyListeners": 48485},
    "2024-12-29": {"followers": 14168, "monthlyListeners": 48120},
    "2025-01-01": {"followers": 14370, "monthlyListeners": 47746},
    "2025-01-04": {"followers": 14623, "monthlyListeners": 47291},
    "2025-01-07": {"followers": 14887, "monthlyListeners": 47236},
    "2025-01-10": {"followers": 15103, "monthlyListeners": 46541},
    "2025-01-13": {"followers": 15316, "monthlyListeners": 44903},
    "2025-01-16": {"followers": 15492, "monthlyListeners": 43355},
    "2025-01-19": {"followers": 15683, "monthlyListeners": 41169},
    "2025-01-22": {"followers": 15922, "monthlyListeners": 41097},
    "2025-01-25": {"followers": 16108, "monthlyListeners": 41323},
    "2025-01-28": {"followers": 16262, "monthlyListeners": 41801},
    "2025-01-31": {"followers": 16419, "monthlyListeners": 42017},
    "2025-02-03": {"followers": 16568, "monthlyListeners": 41485},
    "2025-02-06": {"followers": 16698, "monthlyListeners": 41290},
    "2025-02-09": {"followers": 16814, "monthlyListeners": 40632},
    "2025-02-12": {"followers": 16930, "monthlyListeners": 40615},
    "2025-02-15": {"followers": 17077, "monthlyListeners": 40233},
    "2025-02-18": {"followers": 17221, "monthlyListeners": 39542},
    "2025-02-21": {"followers": 17365, "monthlyListeners": 39132},
    "2025-02-24": {"followers": 17497, "monthlyListeners": 38510},
    "2025-02-27": {"followers": 17640, "monthlyListeners": 38334},
    "2025-03-17": {"followers": 18429, "monthlyListeners": 38068},
    "2025-03-22": {"followers": 18638, "monthlyListeners": 38208},
    "2025-03-23": {"followers": 18677, "monthlyListeners": 38293},
    "2025-03-26": {"followers": 18803, "monthlyListeners": 38382},
    "2025-03-29": {"followers": 18942, "monthlyListeners": 38151},
    "2025-04-01": {"followers": 19100, "monthlyListeners": 38296},
    "2025-04-04": {"followers": 19206, "monthlyListeners": 38516},
    "2025-04-07": {"followers": 19304, "monthlyListeners": 38634},
    "2025-04-10": {"followers": 19431, "monthlyListeners": 38748},
    "2025-04-13": {"followers": 19560, "monthlyListeners": 38858},
    "2025-04-16": {"followers": 19674, "monthlyListeners": 38724},
    "2025-04-19": {"followers": 19832, "monthlyListeners": 38478},
    "2025-04-22": {"followers": 19962, "monthlyListeners": 38540},
    "2025-04-25": {"followers": 20098, "monthlyListeners": 38582},
    "2025-04-28": {"followers": 20231, "monthlyListeners": 38475},
    "2025-05-01": {"followers": 20362, "monthlyListeners": 38380},
    "2025-05-04": {"followers": 20496, "monthlyListeners": 38294},
    "2025-05-07": {"followers": 20630, "monthlyListeners": 38155},
    "2025-05-10": {"followers": 20760, "monthlyListeners": 38515},
    "2025-05-13": {"followers": 20925, "monthlyListeners": 38607},
    "2025-05-16": {"followers": 21120, "monthlyListeners": 39902},
    "2025-05-19": {"followers": 21299, "monthlyListeners": 40125},
    "2025-05-22": {"followers": 21449, "monthlyListeners": 40796},
    "2025-05-25": {"followers": 21587, "monthlyListeners": 41408},
    "2025-05-28": {"followers": 21728, "monthlyListeners": 41774},
    "2025-05-31": {"followers": 21868, "monthlyListeners": 41954},
    "2025-06-03": {"followers": 21994, "monthlyListeners": 42085},
    "2025-06-06": {"followers": 22124, "monthlyListeners": 41969},
    "2025-06-09": {"followers": 22246, "monthlyListeners": 41752},
    "2025-06-12": {"followers": 22344, "monthlyListeners": 41016},
    "2025-06-15": {"followers": 22467, "monthlyListeners": 40763},
    "2025-06-18": {"followers": 22570, "monthlyListeners": 40644},
    "2025-06-21": {"followers": 22683, "monthlyListeners": 39791},
    "2025-06-24": {"followers": 22856, "monthlyListeners": 40982},
    "2025-06-27": {"followers": 23017, "monthlyListeners": 42402},
    "2025-07-01": {"followers": 23138, "monthlyListeners": 43343},
    "2025-07-03": {"followers": 23251, "monthlyListeners": 44023},
    "2025-07-06": {"followers": 23319, "monthlyListeners": 44779},
    "2025-07-09": {"followers": 23410, "monthlyListeners": 44903},
    "2025-07-12": {"followers": 23509, "monthlyListeners": 45000},
    "2025-07-15": {"followers": 23612, "monthlyListeners": 45359},
    "2025-07-18": {"followers": 23708, "monthlyListeners": 45809},
    "2025-07-21": {"followers": 23793, "monthlyListeners": 45644},
    "2025-07-24": {"followers": 23869, "monthlyListeners": 44408},
    "2025-07-27": {"followers": 23953, "monthlyListeners": 43376},
    "2025-07-30": {"followers": 24045, "monthlyListeners": 43097},
    "2025-08-02": {"followers": 24145, "monthlyListeners": 42254},
    "2025-08-05": {"followers": 24259, "monthlyListeners": 41940}
  }
}