{
  "generations": [
    ["Holostars JP", "2"]
  ],
  "id": "49VPZqdN3rQ9oHtkHrIfNN",
  "name": "Yukoku Roberu",
  "stats": {
    "2024-06-25": {"followers": 1978, "monthlyListeners": 3315},
    "2024-06-26": {"followers": 1979, "monthlyListeners": 3295},
    "2024-06-29": {"followers": 1983, "monthlyListeners": 3284},
    "2024-07-02": {"followers": 1983, "monthlyListeners": 3226},
    "2024-07-08": {"followers": 1985, "monthlyListeners": 3058},
    "2024-07-11": {"followers": 1988, "monthlyListeners": 2965},
    "2024-07-14": {"followers": 1992, "monthlyListeners": 2972},
    "2024-07-17": {"followers": 1992, "monthlyListeners": 2864}
  }
}