{
  "generations": [
    ["Holostars JP", "3"]
  ],
  "id": "51y5hQaDx7FLqH0Lcm6ubZ",
  "name": "Aragami Oga",
  "stats": {
    "2024-06-25": {"followers": 2011, "monthlyListeners": 5644},
    "2024-06-26": {"followers": 2011, "monthlyListeners": 5616},
    "2024-06-29": {"followers": 2018, "monthlyListeners": 5594},
    "2024-07-02": {"followers": 2026, "monthlyListeners": 5567},
    "2024-07-08": {"followers": 2040, "monthlyListeners": 5299},
    "2024-07-11": {"followers": 2047, "monthlyListeners": 5229},
    "2024-07-14": {"followers": 2050, "monthlyListeners": 5200},
    "2024-07-17": {"followers": 2052, "monthlyListeners": 5125},
    "2024-07-20": {"followers": 2060, "monthlyListeners": 5081},
    "2024-07-23": {"followers": 2064, "monthlyListeners": 5079},
    "2024-07-26": {"followers": 2068, "monthlyListeners": 4986},
    "2024-07-29": {"followers": 2068, "monthlyListeners": 4948},
    "2024-08-01": {"followers": 2081, "monthlyListeners": 4887},
    "2024-08-04": {"followers": 2085, "monthlyListeners": 4853},
    "2024-08-07": {"followers": 2085, "monthlyListeners": 4804},
    "2024-08-13": {"followers": 2084, "monthlyListeners": 4709},
    "2024-08-16": {"followers": 2085, "monthlyListeners": 4672},
    "2024-08-28": {"followers": 2093, "monthlyListeners": 4499},
    "2024-08-31": {"followers": 2095, "monthlyListeners": 4470},
    "2024-09-03": {"followers": 2096, "monthlyListeners": 4423},
    "2024-09-06": {"followers": 2098, "monthlyListeners": 4417},
    "2024-09-09": {"followers": 2100, "monthlyListeners": 4404},
    "2024-09-12": {"followers": 2099, "monthlyListeners": 4448},
    "2024-09-15": {"followers": 2103, "monthlyListeners": 4482},
    "2024-09-18": {"followers": 2105, "monthlyListeners": 4496},
    "2024-09-21": {"followers": 2106, "monthlyListeners": 4482},
    "2024-09-24": {"followers": 2111, "monthlyListeners": 4468},
    "2024-09-27": {"followers": 2115, "monthlyListeners": 4506},
    "2024-09-30": {"followers": 2123, "monthlyListeners": 4503},
    "2024-10-03": {"followers": 2125, "monthlyListeners": 4556},
    "2024-10-06": {"followers": 2129, "monthlyListeners": 4599},
    "2024-10-09": {"followers": 2127, "monthlyListeners": 4610},
    "2024-10-12": {"followers": 2128, "monthlyListeners": 4568},
    "2024-10-15": {"followers": 2129, "monthlyListeners": 4568},
    "2024-10-18": {"followers": 2135, "monthlyListeners": 4597},
    "2024-10-21": {"followers": 2142, "monthlyListeners": 4615},
    "2024-10-24": {"followers": 2143, "monthlyListeners": 4631},
    "2024-10-27": {"followers": 2151, "monthlyListeners": 4617},
    "2024-10-30": {"followers": 2158, "monthlyListeners": 4608},
    "2024-11-02": {"followers": 2164, "monthlyListeners": 4585},
    "2024-11-05": {"followers": 2167, "monthlyListeners": 4552},
    "2024-11-08": {"followers": 2169, "monthlyListeners": 4507},
    "2024-11-11": {"followers": 2175, "monthlyListeners": 4479},
    "2024-11-14": {"followers": 2180, "monthlyListeners": 4498},
    "2024-11-17": {"followers": 2180, "monthlyListeners": 4481},
    "2024-11-20": {"followers": 2183, "monthlyListeners": 4553},
    "2024-11-23": {"followers": 2183, "monthlyListeners": 4564},
    "2024-11-26": {"followers": 2188, "monthlyListeners": 4522},
    "2024-11-29": {"followers": 2191, "monthlyListeners": 4564},
    "2024-12-02": {"followers": 2194, "monthlyListeners": 4588},
    "2024-12-05": {"followers": 2195, "monthlyListeners": 4698},
    "2024-12-08": {"followers": 2201, "monthlyListeners": 4742},
    "2024-12-11": {"followers": 2209, "monthlyListeners": 4763},
    "2024-12-14": {"followers": 2214, "monthlyListeners": 4751},
    "2024-12-17": {"followers": 2220, "monthlyListeners": 4730},
    "2024-12-20": {"followers": 2222, "monthlyListeners": 4712},
    "2024-12-23": {"followers": 2226, "monthlyListeners": 4700},
    "2024-12-26": {"followers": 2233, "monthlyListeners": 4615},
    "2024-12-29": {"followers": 2236, "monthlyListeners": 4604},
    "2025-01-01": {"followers": 2241, "monthlyListeners": 4533},
    "2025-01-04": {"followers": 2243, "monthlyListeners": 4404},
    "2025-01-07": {"followers": 2245, "monthlyListeners": 4388},
    "2025-01-10": {"followers": 2249, "monthlyListeners": 4386},
    "2025-01-13": {"followers": 2252, "monthlyListeners": 4408},
    "2025-01-16": {"followers": 2256, "monthlyListeners": 4398},
    "2025-01-19": {"followers": 2261, "monthlyListeners": 4406},
    "2025-01-22": {"followers": 2271, "monthlyListeners": 4460},
    "2025-01-25": {"followers": 2274, "monthlyListeners": 4475},
    "2025-01-28": {"followers": 2277, "monthlyListeners": 4465},
    "2025-01-31": {"followers": 2280, "monthlyListeners": 4533},
    "2025-02-03": {"followers": 2285, "monthlyListeners": 4571},
    "2025-02-06": {"followers": 2336, "monthlyListeners": 5106},
    "2025-02-09": {"followers": 2342, "monthlyListeners": 5082},
    "2025-02-12": {"followers": 2347, "monthlyListeners": 5067},
    "2025-02-15": {"followers": 2355, "monthlyListeners": 5043},
    "2025-02-18": {"followers": 2364, "monthlyListeners": 5034},
    "2025-02-21": {"followers": 2368, "monthlyListeners": 5021},
    "2025-02-24": {"followers": 2372, "monthlyListeners": 5005}
  }
}