{
  "generations": [
    ["Holostars JP", "3"]
  ],
  "id": "6Pjq6W7ZAitxgTvUfa9gGk",
  "name": "Kageyama Shien",
  "stats": {
    "2024-06-25": {"followers": 2533, "monthlyListeners": 3274},
    "2024-06-26": {"followers": 2535, "monthlyListeners": 3269},
    "2024-06-29": {"followers": 2544, "monthlyListeners": 3270},
    "2024-07-02": {"followers": 2553, "monthlyListeners": 3208},
    "2024-07-08": {"followers": 2567, "monthlyListeners": 3007},
    "2024-07-11": {"followers": 2576, "monthlyListeners": 2912}
  }
}