{
  "branch": "EN",
  "generation": "Council",
  "generations": [
    "Council",
    "Promise"
  ],
  "id": "3h5FLKIAPF9O96Sdz2j4Jb",
  "name": "Hakos Baelz",
  "stats": {
    "2023-09-04": {"monthlyListeners": 106835},
    "2023-10-04": {"monthlyListeners": 104112},
    "2023-11-05": {"monthlyListeners": 95288},
    "2023-12-04": {"monthlyListeners": 95010},
    "2024-01-06": {"followers": 40726, "monthlyListeners": 96909, "topCities": {"items": [{"city": "Tokyo", "country": "JP", "numberOfListeners": 3295, "region": "13"}, {"city": "Jakarta", "country": "ID", "numberOfListeners": 1618, "region": "JK"}, {"city": "Singapore", "country": "SG", "numberOfListeners": 1449, "region": ""}, {"city": "Kuala Lumpur", "country": "MY", "numberOfListeners": 1171, "region": "14"}, {"city": "Taipei", "country": "TW", "numberOfListeners": 1164, "region": "TPE"}]}, "worldRank": 0},
    "2024-01-07": {"followers": 40777, "monthlyListeners": 96976, "topCities": {"items": [{"city": "Tokyo", "country": "JP", "numberOfListeners": 3314, "region": "13"}, {"city": "Jakarta", "country": "ID", "numberOfListeners": 1639, "region": "JK"}, {"city": "Singapore", "country": "SG", "numberOfListeners": 1469, "region": ""}, {"city": "Kuala Lumpur", "country": "MY", "numberOfListeners": 1190, "region": "14"}, {"city": "Taipei", "country": "TW", "numberOfListeners": 1176, "region": "TPE"}]}, "worldRank": 0},
    "2024-01-10": {"followers": 40923, "monthlyListeners": 96929, "topCities": {"items": [{"city": "Tokyo", "country": "JP", "numberOfListeners": 3404, "region": "13"}, {"city": "Jakarta", "country": "ID", "numberOfListeners": 1676, "region": "JK"}, {"city": "Singapore", "country": "SG", "numberOfListeners": 1466, "region": ""}, {"city": "Kuala Lumpur", "country": "MY", "numberOfListeners": 1201, "region": "14"}, {"city": "Taipei", "country": "TW", "numberOfListeners": 1175, "region": "TPE"}]}, "worldRank": 0},
    "2024-01-17": {"followers": 41279, "monthlyListeners": 97688, "topCities": {"items": [{"city": "Tokyo", "country": "JP", "numberOfListeners": 3650, "region": "13"}, {"city": "Jakarta", "country": "ID", "numberOfListeners": 1723, "region": "JK"}, {"city": "Singapore", "country": "SG", "numberOfListeners": 1499, "region": ""}, {"city": "Kuala Lumpur", "country": "MY", "numberOfListeners": 1256, "region": "14"}, {"city": "Taipei", "country": "TW", "numberOfListeners": 1160, "region": "TPE"}]}, "worldRank": 0},
    "2024-01-19": {"followers": 41412, "monthlyListeners": 98114, "topCities": {"items": [{"city": "Tokyo", "country": "JP", "numberOfListeners": 3812, "region": "13"}, {"city": "Jakarta", "country": "ID", "numberOfListeners": 1740, "region": "JK"}, {"city": "Singapore", "country": "SG", "numberOfListeners": 1515, "region": ""}, {"city": "Kuala Lumpur", "country": "MY", "numberOfListeners": 1258, "region": "14"}, {"city": "Taipei", "country": "TW", "numberOfListeners": 1153, "region": "TPE"}]}, "worldRank": 0},
    "2024-01-21": {"followers": 41509, "monthlyListeners": 98520, "topCities": {"items": [{"city": "Tokyo", "country": "JP", "numberOfListeners": 3902, "region": "13"}, {"city": "Jakarta", "country": "ID", "numberOfListeners": 1766, "region": "JK"}, {"city": "Singapore", "country": "SG", "numberOfListeners": 1496, "region": ""}, {"city": "Kuala Lumpur", "country": "MY", "numberOfListeners": 1252, "region": "14"}, {"city": "Taipei", "country": "TW", "numberOfListeners": 1169, "region": "TPE"}]}, "top_tracks_playcount": [2422531, 4103349, 1376738, 523087, 141558, 439006, 794885, 346085, 32999, 185672], "worldRank": 0},
    "2024-01-22": {"followers": 41566, "monthlyListeners": 98816, "topCities": {"items": [{"city": "Tokyo", "country": "JP", "numberOfListeners": 3925, "region": "13"}, {"city": "Jakarta", "country": "ID", "numberOfListeners": 1780, "region": "JK"}, {"city": "Singapore", "country": "SG", "numberOfListeners": 1506, "region": ""}, {"city": "Kuala Lumpur", "country": "MY", "numberOfListeners": 1244, "region": "14"}, {"city": "Taipei", "country": "TW", "numberOfListeners": 1169, "region": "TPE"}]}, "top_tracks_playcount": [2427810, 4107803, 1382084, 524747, 142946, 440104, 795910, 346992, 34043, 186088], "worldRank": 0},
    "2024-01-25": {"followers": 41715, "monthlyListeners": 100281, "topCities": {"items": [{"city": "Tokyo", "country": "JP", "numberOfListeners": 4077, "region": "13"}, {"city": "Jakarta", "country": "ID", "numberOfListeners": 1816, "region": "JK"}, {"city": "Singapore", "country": "SG", "numberOfListeners": 1547, "region": ""}, {"city": "Kuala Lumpur", "country": "MY", "numberOfListeners": 1234, "region": "14"}, {"city": "Taipei", "country": "TW", "numberOfListeners": 1172, "region": "TPE"}]}, "top_tracks_playcount": [2447548, 4123479, 1391062, 531071, 147707, 444096, 799551, 350605, 37006, 187781], "worldRank": 0},
    "2024-01-28": {"followers": 41845, "monthlyListeners": 100031, "topCities": {"items": [{"city": "Tokyo", "country": "JP", "numberOfListeners": 4095, "region": "13"}, {"city": "Jakarta", "country": "ID", "numberOfListeners": 1822, "region": "JK"}, {"city": "Singapore", "country": "SG", "numberOfListeners": 1523, "region": ""}, {"city": "Kuala Lumpur", "country": "MY", "numberOfListeners": 1207, "region": "14"}, {"city": "Los Angeles", "country": "US", "numberOfListeners": 1167, "region": "CA"}]}, "top_tracks_playcount": [2466768, 4139003, 1399545, 536425, 152086, 448203, 802956, 353430, 39667, 189365], "worldRank": 0},
    "2024-01-31": {"followers": 41953, "monthlyListeners": 99872, "topCities": {"items": [{"city": "Tokyo", "country": "JP", "numberOfListeners": 4171, "region": "13"}, {"city": "Jakarta", "country": "ID", "numberOfListeners": 1802, "region": "JK"}, {"city": "Singapore", "country": "SG", "numberOfListeners": 1509, "region": ""}, {"city": "Los Angeles", "country": "US", "numberOfListeners": 1192, "region": "CA"}, {"city": "Kuala Lumpur", "country": "MY", "numberOfListeners": 1178, "region": "14"}]}, "top_tracks_playcount": [2485461, 4153757, 1407990, 541867, 156433, 451938, 806165, 356769, 42170, 190903], "worldRank": 0},
    "2024-02-03": {"followers": 42117, "monthlyListeners": 98918, "topCities": {"items": [{"city": "Tokyo", "country": "JP", "numberOfListeners": 4137, "region": "13"}, {"city": "Jakarta", "country": "ID", "numberOfListeners": 1784, "region": "JK"}, {"city": "Singapore", "country": "SG", "numberOfListeners": 1473, "region": ""}, {"city": "Los Angeles", "country": "US", "numberOfListeners": 1216, "region": "CA"}, {"city": "Kuala Lumpur", "country": "MY", "numberOfListeners": 1174, "region": "14"}]}, "top_tracks_playcount": [2504182, 4168782, 1416592, 547774, 160711, 455782, 809528, 359872, 45044, 192391], "worldRank": 0},
    "2024-02-06": {"followers": 42241, "monthlyListeners": 98078, "topCities": {"items": [{"city": "Tokyo", "country": "JP", "numberOfListeners": 4148, "region": "13"}, {"city": "Jakarta", "country": "ID", "numberOfListeners": 1726, "region": "JK"}, {"city": "Singapore", "country": "SG", "numberOfListeners": 1476, "region": ""}, {"city": "Los Angeles", "country": "US", "numberOfListeners": 1192, "region": "CA"}, {"city": "Kuala Lumpur", "country": "MY", "numberOfListeners": 1179, "region": "14"}]}, "top_tracks_playcount": [2521085, 4181817, 1424267, 552765, 164528, 459463, 812488, 362640, 47776, 193714], "worldRank": 0},
    "2024-02-09": {"followers": 42359, "monthlyListeners": 97503, "topCities": {"items": [{"city": "Tokyo", "country": "JP", "numberOfListeners": 4101, "region": "13"}, {"city": "Jakarta", "country": "ID", "numberOfListeners": 1705, "region": "JK"}, {"city": "Singapore", "country": "SG", "numberOfListeners": 1448, "region": ""}, {"city": "Los Angeles", "country": "US", "numberOfListeners": 1169, "region": "CA"}, {"city": "Kuala Lumpur", "country": "MY", "numberOfListeners": 1160, "region": "14"}]}, "top_tracks_playcount": [2539481, 4196880, 1432578, 558924, 168748, 463546, 815822, 365617, 50877, 195087], "worldRank": 0},
    "2024-02-12": {"followers": 42474, "monthlyListeners": 96872, "topCities": {"items": [{"city": "Tokyo", "country": "JP", "numberOfListeners": 4090, "region": "13"}, {"city": "Jakarta", "country": "ID", "numberOfListeners": 1689, "region": "JK"}, {"city": "Singapore", "country": "SG", "numberOfListeners": 1422, "region": ""}, {"city": "Los Angeles", "country": "US", "numberOfListeners": 1152, "region": "CA"}, {"city": "Kuala Lumpur", "country": "MY", "numberOfListeners": 1152, "region": "14"}]}, "top_tracks_playcount": [2556993, 4209816, 1439757, 563841, 172457, 466603, 818566, 368230, 53671, 196430], "worldRank": 0},
    "2024-02-15": {"followers": 42594, "monthlyListeners": 97241, "topCities": {"items": [{"city": "Tokyo", "country": "JP", "numberOfListeners": 4078, "region": "13"}, {"city": "Jakarta", "country": "ID", "numberOfListeners": 1674, "region": "JK"}, {"city": "Singapore", "country": "SG", "numberOfListeners": 1410, "region": ""}, {"city": "Los Angeles", "country": "US", "numberOfListeners": 1142, "region": "CA"}, {"city": "Kuala Lumpur", "country": "MY", "numberOfListeners": 1141, "region": "14"}]}, "top_tracks_playcount": [2578476, 4224474, 1447951, 569816, 176650, 470571, 821576, 371284, 56656, 197922], "worldRank": 0},
    "2024-02-18": {"followers": 42735, "monthlyListeners": 97493, "topCities": {"items": [{"city": "Tokyo", "country": "JP", "numberOfListeners": 4003, "region": "13"}, {"city": "Jakarta", "country": "ID", "numberOfListeners": 1648, "region": "JK"}, {"city": "Singapore", "country": "SG", "numberOfListeners": 1408, "region": ""}, {"city": "Los Angeles", "country": "US", "numberOfListeners": 1157, "region": "CA"}, {"city": "Kuala Lumpur", "country": "MY", "numberOfListeners": 1146, "region": "14"}]}, "top_tracks_playcount": [2598151, 4238473, 1455718, 575564, 180608, 474265, 824497, 373975, 59424, 199494], "worldRank": 0},
    "2024-02-21": {"followers": 42841, "monthlyListeners": 97452, "topCities": {"items": [{"city": "Tokyo", "country": "JP", "numberOfListeners": 4028, "region": "13"}, {"city": "Jakarta", "country": "ID", "numberOfListeners": 1647, "region": "JK"}, {"city": "Singapore", "country": "SG", "numberOfListeners": 1405, "region": ""}, {"city": "Kuala Lumpur", "country": "MY", "numberOfListeners": 1161, "region": "14"}, {"city": "Los Angeles", "country": "US", "numberOfListeners": 1142, "region": "CA"}]}, "top_tracks_playcount": [2610517, 4247153, 1460802, 578994, 183187, 476416, 826288, 376099, 61155, 200662], "worldRank": 0},
    "2024-02-24": {"followers": 42977, "monthlyListeners": 97377, "topCities": {"items": [{"city": "Tokyo", "country": "JP", "numberOfListeners": 3990, "region": "13"}, {"city": "Jakarta", "country": "ID", "numberOfListeners": 1629, "region": "JK"}, {"city": "Singapore", "country": "SG", "numberOfListeners": 1407, "region": ""}, {"city": "Kuala Lumpur", "country": "MY", "numberOfListeners": 1171, "region": "14"}, {"city": "Taipei", "country": "TW", "numberOfListeners": 1150, "region": "TPE"}]}, "top_tracks_playcount": [2635842, 4266674, 1472261, 586749, 188598, 481311, 830380, 380049, 64671, 202639], "worldRank": 0},
    "2024-02-27": {"followers": 43120, "monthlyListeners": 97766, "topCities": {"items": [{"city": "Tokyo", "country": "JP", "numberOfListeners": 3984, "region": "13"}, {"city": "Jakarta", "country": "ID", "numberOfListeners": 1627, "region": "JK"}, {"city": "Singapore", "country": "SG", "numberOfListeners": 1428, "region": ""}, {"city": "Taipei", "country": "TW", "numberOfListeners": 1189, "region": "TPE"}, {"city": "Kuala Lumpur", "country": "MY", "numberOfListeners": 1183, "region": "14"}]}, "top_tracks_playcount": [2653370, 4279635, 1479902, 592097, 192403, 485287, 833198, 382714, 67201, 204049], "worldRank": 0},
    "2024-03-01": {"followers": 44244, "monthlyListeners": 101376, "topCities": {"items": [{"city": "Tokyo", "country": "JP", "numberOfListeners": 4162, "region": "13"}, {"city": "Jakarta", "country": "ID", "numberOfListeners": 1666, "region": "JK"}, {"city": "Singapore", "country": "SG", "numberOfListeners": 1479, "region": ""}, {"city": "Kuala Lumpur", "country": "MY", "numberOfListeners": 1235, "region": "14"}, {"city": "Taipei", "country": "TW", "numberOfListeners": 1222, "region": "TPE"}]}, "top_tracks_playcount": [2675371, 4293822, 1488337, 598579, 198770, 490229, 836726, 386467, 72858, 205749], "worldRank": 0},
    "2024-03-04": {"followers": 44844, "monthlyListeners": 106446, "topCities": {"items": [{"city": "Tokyo", "country": "JP", "numberOfListeners": 4453, "region": "13"}, {"city": "Jakarta", "country": "ID", "numberOfListeners": 1749, "region": "JK"}, {"city": "Singapore", "country": "SG", "numberOfListeners": 1565, "region": ""}, {"city": "Taipei", "country": "TW", "numberOfListeners": 1319, "region": "TPE"}, {"city": "Kuala Lumpur", "country": "MY", "numberOfListeners": 1312, "region": "14"}]}, "top_tracks_playcount": [2695628, 4307969, 1496375, 213687, 604560, 88880, 37387, 495063, 839902, 389734], "worldRank": 0},
    "2024-03-07": {"followers": 45210, "monthlyListeners": 111531, "topCities": {"items": [{"city": "Tokyo", "country": "JP", "numberOfListeners": 4724, "region": "13"}, {"city": "Jakarta", "country": "ID", "numberOfListeners": 1816, "region": "JK"}, {"city": "Singapore", "country": "SG", "numberOfListeners": 1645, "region": ""}, {"city": "Taipei", "country": "TW", "numberOfListeners": 1425, "region": "TPE"}, {"city": "Kuala Lumpur", "country": "MY", "numberOfListeners": 1394, "region": "14"}]}, "top_tracks_playcount": [2719328, 4322319, 1504814, 63674, 225625, 612121, 100295, 46663, 38012, 500454], "worldRank": 0},
    "2024-03-10": {"followers": 45449, "monthlyListeners": 115046, "topCities": {"items": [{"city": "Tokyo", "country": "JP", "numberOfListeners": 5022, "region": "13"}, {"city": "Jakarta", "country": "ID", "numberOfListeners": 1860, "region": "JK"}, {"city": "Singapore", "country": "SG", "numberOfListeners": 1714, "region": ""}, {"city": "Taipei", "country": "TW", "numberOfListeners": 1488, "region": "TPE"}, {"city": "Kuala Lumpur", "country": "MY", "numberOfListeners": 1436, "region": "14"}]}, "top_tracks_playcount": [2740400, 4335660, 85587, 1512850, 235096, 60613, 108675, 618525, 48492, 41810], "worldRank": 0},
    "2024-03-13": {"followers": 45663, "monthlyListeners": 117761, "topCities": {"items": [{"city": "Tokyo", "country": "JP", "numberOfListeners": 5248, "region": "13"}, {"city": "Jakarta", "country": "ID", "numberOfListeners": 1863, "region": "JK"}, {"city": "Singapore", "country": "SG", "numberOfListeners": 1751, "region": ""}, {"city": "Taipei", "country": "TW", "numberOfListeners": 1532, "region": "TPE"}, {"city": "Kuala Lumpur", "country": "MY", "numberOfListeners": 1425, "region": "14"}]}, "top_tracks_playcount": [2760978, 4348629, 104519, 1521492, 72853, 243465, 115811, 624811, 57304, 49181], "worldRank": 0},
    "2024-03-19": {"followers": 46082, "monthlyListeners": 121860, "topCities": {"items": [{"city": "Tokyo", "country": "JP", "numberOfListeners": 6018, "region": "13"}, {"city": "Jakarta", "country": "ID", "numberOfListeners": 1908, "region": "JK"}, {"city": "Singapore", "country": "SG", "numberOfListeners": 1818, "region": ""}, {"city": "Taipei", "country": "TW", "numberOfListeners": 1608, "region": "TPE"}, {"city": "Kuala Lumpur", "country": "MY", "numberOfListeners": 1447, "region": "14"}]}, "top_tracks_playcount": [2793759, 4370801, 130809, 89895, 1535000, 255693, 70559, 126230, 634707, 59626], "worldRank": 0},
    "2024-03-22": {"followers": 46313, "monthlyListeners": 123607, "topCities": {"items": [{"city": "Tokyo", "country": "JP", "numberOfListeners": 6176, "region": "13"}, {"city": "Jakarta", "country": "ID", "numberOfListeners": 1919, "region": "JK"}, {"city": "Singapore", "country": "SG", "numberOfListeners": 1829, "region": ""}, {"city": "Taipei", "country": "TW", "numberOfListeners": 1648, "region": "TPE"}, {"city": "Kuala Lumpur", "country": "MY", "numberOfListeners": 1471, "region": "14"}]}, "top_tracks_playcount": [2823110, 4389284, 151121, 103494, 1546413, 265388, 79869, 134610, 643005, 67576], "worldRank": 0},
    "2024-03-25": {"followers": 46510, "monthlyListeners": 124586, "topCities": {"items": [{"city": "Tokyo", "country": "JP", "numberOfListeners": 6308, "region": "13"}, {"city": "Jakarta", "country": "ID", "numberOfListeners": 1930, "region": "JK"}, {"city": "Singapore", "country": "SG", "numberOfListeners": 1842, "region": ""}, {"city": "Taipei", "country": "TW", "numberOfListeners": 1668, "region": "TPE"}, {"city": "Los Angeles", "country": "US", "numberOfListeners": 1485, "region": "CA"}]}, "top_tracks_playcount": [2843560, 4402008, 163358, 111954, 1554111, 271820, 85621, 139858, 648517, 72296], "worldRank": 0},
    "2024-03-28": {"followers": 46669, "monthlyListeners": 124631, "topCities": {"items": [{"city": "Tokyo", "country": "JP", "numberOfListeners": 6394, "region": "13"}, {"city": "Jakarta", "country": "ID", "numberOfListeners": 1935, "region": "JK"}, {"city": "Singapore", "country": "SG", "numberOfListeners": 1863, "region": ""}, {"city": "Taipei", "country": "TW", "numberOfListeners": 1684, "region": "TPE"}, {"city": "Los Angeles", "country": "US", "numberOfListeners": 1494, "region": "CA"}]}, "top_tracks_playcount": [2865679, 4415960, 175794, 119918, 1562502, 278267, 91565, 145071, 654356, 76939], "worldRank": 0},
    "2024-03-31": {"followers": 46881, "monthlyListeners": 122304, "topCities": {"items": [{"city": "Tokyo", "country": "JP", "numberOfListeners": 6404, "region": "13"}, {"city": "Jakarta", "country": "ID", "numberOfListeners": 1884, "region": "JK"}, {"city": "Singapore", "country": "SG", "numberOfListeners": 1801, "region": ""}, {"city": "Taipei", "country": "TW", "numberOfListeners": 1644, "region": "TPE"}, {"city": "Los Angeles", "country": "US", "numberOfListeners": 1487, "region": "CA"}]}, "top_tracks_playcount": [2884935, 4428430, 186606, 127798, 1570402, 284129, 96509, 149950, 659716, 81514], "worldRank": 0},
    "2024-04-03": {"followers": 47046, "monthlyListeners": 120602, "topCities": {"items": [{"city": "Tokyo", "country": "JP", "numberOfListeners": 6454, "region": "13"}, {"city": "Jakarta", "country": "ID", "numberOfListeners": 1853, "region": "JK"}, {"city": "Singapore", "country": "SG", "numberOfListeners": 1774, "region": ""}, {"city": "Taipei", "country": "TW", "numberOfListeners": 1586, "region": "TPE"}, {"city": "Los Angeles", "country": "US", "numberOfListeners": 1475, "region": "CA"}]}, "top_tracks_playcount": [2896835, 4436534, 193144, 132299, 1575197, 287952, 99225, 663167, 152803, 84198], "worldRank": 0},
    "2024-04-06": {"followers": 47238, "monthlyListeners": 117457, "topCities": {"items": [{"city": "Tokyo", "country": "JP", "numberOfListeners": 6329, "region": "13"}, {"city": "Jakarta", "country": "ID", "numberOfListeners": 1814, "region": "JK"}, {"city": "Singapore", "country": "SG", "numberOfListeners": 1726, "region": ""}, {"city": "Taipei", "country": "TW", "numberOfListeners": 1464, "region": "TPE"}, {"city": "Los Angeles", "country": "US", "numberOfListeners": 1448, "region": "CA"}]}, "top_tracks_playcount": [2925615, 4455084, 207642, 141885, 1585963, 295821, 105329, 670869, 159408, 89805], "worldRank": 0},
    "2024-04-09": {"followers": 47410, "monthlyListeners": 116968, "topCities": {"items": [{"city": "Tokyo", "country": "JP", "numberOfListeners": 6292, "region": "13"}, {"city": "Jakarta", "country": "ID", "numberOfListeners": 1815, "region": "JK"}, {"city": "Singapore", "country": "SG", "numberOfListeners": 1696, "region": ""}, {"city": "Los Angeles", "country": "US", "numberOfListeners": 1460, "region": "CA"}, {"city": "Taipei", "country": "TW", "numberOfListeners": 1449, "region": "TPE"}]}, "top_tracks_playcount": [2939164, 4463425, 213391, 1590775, 145877, 299284, 674277, 107938, 162228, 92166], "worldRank": 0},
    "2024-04-12": {"followers": 47593, "monthlyListeners": 115377, "topCities": {"items": [{"city": "Tokyo", "country": "JP", "numberOfListeners": 6210, "region": "13"}, {"city": "Jakarta", "country": "ID", "numberOfListeners": 1837, "region": "JK"}, {"city": "Singapore", "country": "SG", "numberOfListeners": 1662, "region": ""}, {"city": "Los Angeles", "country": "US", "numberOfListeners": 1506, "region": "CA"}, {"city": "Taipei", "country": "TW", "numberOfListeners": 1384, "region": "TPE"}]}, "top_tracks_playcount": [2971168, 4481605, 226859, 1600875, 154747, 306964, 681922, 113722, 168458, 97370], "worldRank": 0}
  }
}