{
  "branch": "EN",
  "generation": "Myth",
  "id": "3iPvwu8p75fYRa0V4wi8gN",
  "name": "Ninomae Ina'nis",
  "stats": {
    "2023-09-04": {"monthlyListeners": 90125},
    "2023-10-04": {"monthlyListeners": 89367},
    "2023-11-05": {"monthlyListeners": 80527},
    "2023-12-04": {"monthlyListeners": 79541},
    "2024-01-06": {"followers": 35622, "monthlyListeners": 76798, "topCities": {"items": [{"city": "Tokyo", "country": "JP", "numberOfListeners": 3583, "region": "13"}, {"city": "Jakarta", "country": "ID", "numberOfListeners": 1898, "region": "JK"}, {"city": "Taipei", "country": "TW", "numberOfListeners": 1430, "region": "TPE"}, {"city": "Singapore", "country": "SG", "numberOfListeners": 1332, "region": ""}, {"city": "Kuala Lumpur", "country": "MY", "numberOfListeners": 1232, "region": "14"}]}, "worldRank": 0},
    "2024-01-07": {"followers": 35647, "monthlyListeners": 76872, "topCities": {"items": [{"city": "Tokyo", "country": "JP", "numberOfListeners": 3566, "region": "13"}, {"city": "Jakarta", "country": "ID", "numberOfListeners": 1906, "region": "JK"}, {"city": "Taipei", "country": "TW", "numberOfListeners": 1429, "region": "TPE"}, {"city": "Singapore", "country": "SG", "numberOfListeners": 1340, "region": ""}, {"city": "Kuala Lumpur", "country": "MY", "numberOfListeners": 1219, "region": "14"}]}, "worldRank": 0},
    "2024-01-10": {"followers": 35725, "monthlyListeners": 76859, "topCities": {"items": [{"city": "Tokyo", "country": "JP", "numberOfListeners": 3604, "region": "13"}, {"city": "Jakarta", "country": "ID", "numberOfListeners": 1912, "region": "JK"}, {"city": "Taipei", "country": "TW", "numberOfListeners": 1414, "region": "TPE"}, {"city": "Singapore", "country": "SG", "numberOfListeners": 1334, "region": ""}, {"city": "Kuala Lumpur", "country": "MY", "numberOfListeners": 1230, "region": "14"}]}, "worldRank": 0},
    "2024-01-17": {"followers": 35902, "monthlyListeners": 84947, "topCities": {"items": [{"city": "Tokyo", "country": "JP", "numberOfListeners": 3802, "region": "13"}, {"city": "Jakarta", "country": "ID", "numberOfListeners": 1941, "region": "JK"}, {"city": "Taipei", "country": "TW", "numberOfListeners": 1517, "region": "TPE"}, {"city": "Singapore", "country": "SG", "numberOfListeners": 1456, "region": ""}, {"city": "Kuala Lumpur", "country": "MY", "numberOfListeners": 1323, "region": "14"}]}, "worldRank": 0},
    "2024-01-19": {"followers": 35964, "monthlyListeners": 88334, "topCities": {"items": [{"city": "Tokyo", "country": "JP", "numberOfListeners": 3935, "region": "13"}, {"city": "Jakarta", "country": "ID", "numberOfListeners": 1982, "region": "JK"}, {"city": "Taipei", "country": "TW", "numberOfListeners": 1563, "region": "TPE"}, {"city": "Singapore", "country": "SG", "numberOfListeners": 1498, "region": ""}, {"city": "Kuala Lumpur", "country": "MY", "numberOfListeners": 1363, "region": "14"}]}, "worldRank": 0},
    "2024-01-21": {"followers": 36018, "monthlyListeners": 89904, "topCities": {"items": [{"city": "Tokyo", "country": "JP", "numberOfListeners": 4036, "region": "13"}, {"city": "Jakarta", "country": "ID", "numberOfListeners": 2004, "region": "JK"}, {"city": "Taipei", "country": "TW", "numberOfListeners": 1583, "region": "TPE"}, {"city": "Singapore", "country": "SG", "numberOfListeners": 1516, "region": ""}, {"city": "Kuala Lumpur", "country": "MY", "numberOfListeners": 1396, "region": "14"}]}, "top_tracks_playcount": [5555666, 1460123, 2175251, 35227, 1610439, 578169, 148038, 1193826, 267347, 1500], "worldRank": 0},
    "2024-01-22": {"followers": 36037, "monthlyListeners": 90420, "topCities": {"items": [{"city": "Tokyo", "country": "JP", "numberOfListeners": 4047, "region": "13"}, {"city": "Jakarta", "country": "ID", "numberOfListeners": 2036, "region": "JK"}, {"city": "Taipei", "country": "TW", "numberOfListeners": 1583, "region": "TPE"}, {"city": "Singapore", "country": "SG", "numberOfListeners": 1522, "region": ""}, {"city": "Kuala Lumpur", "country": "MY", "numberOfListeners": 1391, "region": "14"}]}, "top_tracks_playcount": [5559140, 1462226, 2176987, 36961, 1611520, 578886, 148602, 1194104, 267680, 1558], "worldRank": 0},
    "2024-01-25": {"followers": 36093, "monthlyListeners": 92339, "topCities": {"items": [{"city": "Tokyo", "country": "JP", "numberOfListeners": 4139, "region": "13"}, {"city": "Jakarta", "country": "ID", "numberOfListeners": 2084, "region": "JK"}, {"city": "Taipei", "country": "TW", "numberOfListeners": 1578, "region": "TPE"}, {"city": "Singapore", "country": "SG", "numberOfListeners": 1561, "region": ""}, {"city": "Kuala Lumpur", "country": "MY", "numberOfListeners": 1398, "region": "14"}]}, "top_tracks_playcount": [5570369, 1469415, 2183062, 42833, 1614846, 580947, 150352, 268660, 1195044, 1723], "worldRank": 0},
    "2024-01-28": {"followers": 36144, "monthlyListeners": 93418, "topCities": {"items": [{"city": "Tokyo", "country": "JP", "numberOfListeners": 4187, "region": "13"}, {"city": "Jakarta", "country": "ID", "numberOfListeners": 2117, "region": "JK"}, {"city": "Taipei", "country": "TW", "numberOfListeners": 1593, "region": "TPE"}, {"city": "Singapore", "country": "SG", "numberOfListeners": 1561, "region": ""}, {"city": "Kuala Lumpur", "country": "MY", "numberOfListeners": 1426, "region": "14"}]}, "top_tracks_playcount": [5580415, 1476421, 2188917, 48391, 1618155, 583059, 152032, 1196068, 269422, 1898], "worldRank": 0},
    "2024-01-31": {"followers": 36184, "monthlyListeners": 94392, "topCities": {"items": [{"city": "Tokyo", "country": "JP", "numberOfListeners": 4263, "region": "13"}, {"city": "Jakarta", "country": "ID", "numberOfListeners": 2143, "region": "JK"}, {"city": "Taipei", "country": "TW", "numberOfListeners": 1579, "region": "TPE"}, {"city": "Singapore", "country": "SG", "numberOfListeners": 1537, "region": ""}, {"city": "Kuala Lumpur", "country": "MY", "numberOfListeners": 1436, "region": "14"}]}, "top_tracks_playcount": [5590160, 1483356, 2194342, 52847, 1621525, 585090, 153884, 1197347, 270212, 2005], "worldRank": 0},
    "2024-02-03": {"followers": 36257, "monthlyListeners": 94937, "topCities": {"items": [{"city": "Tokyo", "country": "JP", "numberOfListeners": 4246, "region": "13"}, {"city": "Jakarta", "country": "ID", "numberOfListeners": 2135, "region": "JK"}, {"city": "Taipei", "country": "TW", "numberOfListeners": 1590, "region": "TPE"}, {"city": "Singapore", "country": "SG", "numberOfListeners": 1541, "region": ""}, {"city": "Kuala Lumpur", "country": "MY", "numberOfListeners": 1414, "region": "14"}]}, "top_tracks_playcount": [5600230, 1490249, 2200207, 57764, 1624762, 587050, 155728, 1198268, 270959, 2105], "worldRank": 0},
    "2024-02-06": {"followers": 36308, "monthlyListeners": 94749, "topCities": {"items": [{"city": "Tokyo", "country": "JP", "numberOfListeners": 4204, "region": "13"}, {"city": "Jakarta", "country": "ID", "numberOfListeners": 2097, "region": "JK"}, {"city": "Taipei", "country": "TW", "numberOfListeners": 1597, "region": "TPE"}, {"city": "Singapore", "country": "SG", "numberOfListeners": 1547, "region": ""}, {"city": "Kuala Lumpur", "country": "MY", "numberOfListeners": 1415, "region": "14"}]}, "top_tracks_playcount": [5609509, 1496709, 2205639, 61106, 1628015, 588904, 157479, 1199047, 271725, 2187], "worldRank": 0},
    "2024-02-09": {"followers": 36343, "monthlyListeners": 93948, "topCities": {"items": [{"city": "Tokyo", "country": "JP", "numberOfListeners": 4132, "region": "13"}, {"city": "Jakarta", "country": "ID", "numberOfListeners": 2044, "region": "JK"}, {"city": "Taipei", "country": "TW", "numberOfListeners": 1568, "region": "TPE"}, {"city": "Singapore", "country": "SG", "numberOfListeners": 1515, "region": ""}, {"city": "Kuala Lumpur", "country": "MY", "numberOfListeners": 1394, "region": "14"}]}, "top_tracks_playcount": [5619506, 1503536, 2211304, 64340, 1631293, 590809, 159367, 1199946, 272449, 2253], "worldRank": 0},
    "2024-02-12": {"followers": 36390, "monthlyListeners": 87927, "topCities": {"items": [{"city": "Tokyo", "country": "JP", "numberOfListeners": 4007, "region": "13"}, {"city": "Jakarta", "country": "ID", "numberOfListeners": 2014, "region": "JK"}, {"city": "Taipei", "country": "TW", "numberOfListeners": 1501, "region": "TPE"}, {"city": "Singapore", "country": "SG", "numberOfListeners": 1437, "region": ""}, {"city": "Kuala Lumpur", "country": "MY", "numberOfListeners": 1342, "region": "14"}]}, "top_tracks_playcount": [5629572, 1509438, 2216505, 66957, 1634377, 592635, 160957, 1200879, 273098, 102607], "worldRank": 0},
    "2024-02-15": {"followers": 36439, "monthlyListeners": 83252, "topCities": {"items": [{"city": "Tokyo", "country": "JP", "numberOfListeners": 3824, "region": "13"}, {"city": "Jakarta", "country": "ID", "numberOfListeners": 1958, "region": "JK"}, {"city": "Taipei", "country": "TW", "numberOfListeners": 1435, "region": "TPE"}, {"city": "Singapore", "country": "SG", "numberOfListeners": 1361, "region": ""}, {"city": "Kuala Lumpur", "country": "MY", "numberOfListeners": 1305, "region": "14"}]}, "top_tracks_playcount": [5639704, 1515984, 2222066, 69953, 1637536, 594392, 162728, 1201819, 273731, 102782], "worldRank": 0},
    "2024-02-18": {"followers": 36489, "monthlyListeners": 79979, "topCities": {"items": [{"city": "Tokyo", "country": "JP", "numberOfListeners": 3710, "region": "13"}, {"city": "Jakarta", "country": "ID", "numberOfListeners": 1909, "region": "JK"}, {"city": "Taipei", "country": "TW", "numberOfListeners": 1347, "region": "TPE"}, {"city": "Singapore", "country": "SG", "numberOfListeners": 1312, "region": ""}, {"city": "Kuala Lumpur", "country": "MY", "numberOfListeners": 1262, "region": "14"}]}, "top_tracks_playcount": [5649054, 1522104, 2227159, 72604, 1640713, 596185, 164362, 1202656, 274397, 102887], "worldRank": 0},
    "2024-02-21": {"followers": 36531, "monthlyListeners": 78680, "topCities": {"items": [{"city": "Tokyo", "country": "JP", "numberOfListeners": 3682, "region": "13"}, {"city": "Jakarta", "country": "ID", "numberOfListeners": 1869, "region": "JK"}, {"city": "Taipei", "country": "TW", "numberOfListeners": 1348, "region": "TPE"}, {"city": "Singapore", "country": "SG", "numberOfListeners": 1299, "region": ""}, {"city": "Kuala Lumpur", "country": "MY", "numberOfListeners": 1245, "region": "14"}]}, "top_tracks_playcount": [5655053, 1525917, 2230379, 74450, 1642781, 597412, 165541, 1203131, 274863, 102955], "worldRank": 0},
    "2024-02-24": {"followers": 36599, "monthlyListeners": 76477, "topCities": {"items": [{"city": "Tokyo", "country": "JP", "numberOfListeners": 3563, "region": "13"}, {"city": "Jakarta", "country": "ID", "numberOfListeners": 1838, "region": "JK"}, {"city": "Taipei", "country": "TW", "numberOfListeners": 1387, "region": "TPE"}, {"city": "Singapore", "country": "SG", "numberOfListeners": 1264, "region": ""}, {"city": "Kuala Lumpur", "country": "MY", "numberOfListeners": 1231, "region": "14"}]}, "top_tracks_playcount": [5668336, 1534440, 2237789, 78359, 1646825, 599635, 167830, 1204223, 275715, 103132], "worldRank": 0},
    "2024-02-27": {"followers": 36660, "monthlyListeners": 75181, "topCities": {"items": [{"city": "Tokyo", "country": "JP", "numberOfListeners": 3567, "region": "13"}, {"city": "Jakarta", "country": "ID", "numberOfListeners": 1821, "region": "JK"}, {"city": "Taipei", "country": "TW", "numberOfListeners": 1403, "region": "TPE"}, {"city": "Singapore", "country": "SG", "numberOfListeners": 1242, "region": ""}, {"city": "Kuala Lumpur", "country": "MY", "numberOfListeners": 1224, "region": "14"}]}, "top_tracks_playcount": [5677352, 1540156, 2242699, 80836, 1649822, 601370, 169383, 1205006, 276371, 103240], "worldRank": 0},
    "2024-03-01": {"followers": 36708, "monthlyListeners": 74248, "topCities": {"items": [{"city": "Tokyo", "country": "JP", "numberOfListeners": 3542, "region": "13"}, {"city": "Jakarta", "country": "ID", "numberOfListeners": 1785, "region": "JK"}, {"city": "Taipei", "country": "TW", "numberOfListeners": 1403, "region": "TPE"}, {"city": "Singapore", "country": "SG", "numberOfListeners": 1240, "region": ""}, {"city": "Kuala Lumpur", "country": "MY", "numberOfListeners": 1204, "region": "14"}]}, "top_tracks_playcount": [5687343, 1546486, 2247970, 1652879, 83285, 603170, 171016, 1205851, 277048, 103349], "worldRank": 0},
    "2024-03-04": {"followers": 36772, "monthlyListeners": 73225, "topCities": {"items": [{"city": "Tokyo", "country": "JP", "numberOfListeners": 3533, "region": "13"}, {"city": "Jakarta", "country": "ID", "numberOfListeners": 1754, "region": "JK"}, {"city": "Taipei", "country": "TW", "numberOfListeners": 1386, "region": "TPE"}, {"city": "Singapore", "country": "SG", "numberOfListeners": 1219, "region": ""}, {"city": "Kuala Lumpur", "country": "MY", "numberOfListeners": 1185, "region": "14"}]}, "top_tracks_playcount": [5696690, 1552487, 2252947, 1655855, 85554, 604785, 172463, 1206630, 277794, 103447], "worldRank": 0},
    "2024-03-07": {"followers": 36853, "monthlyListeners": 73011, "topCities": {"items": [{"city": "Tokyo", "country": "JP", "numberOfListeners": 3548, "region": "13"}, {"city": "Jakarta", "country": "ID", "numberOfListeners": 1751, "region": "JK"}, {"city": "Taipei", "country": "TW", "numberOfListeners": 1384, "region": "TPE"}, {"city": "Kuala Lumpur", "country": "MY", "numberOfListeners": 1200, "region": "14"}, {"city": "Singapore", "country": "SG", "numberOfListeners": 1180, "region": ""}]}, "top_tracks_playcount": [5707417, 1558602, 2258065, 1658874, 87927, 606535, 173908, 1207575, 278546, 103557], "worldRank": 0},
    "2024-03-10": {"followers": 36907, "monthlyListeners": 72910, "topCities": {"items": [{"city": "Tokyo", "country": "JP", "numberOfListeners": 3573, "region": "13"}, {"city": "Jakarta", "country": "ID", "numberOfListeners": 1786, "region": "JK"}, {"city": "Taipei", "country": "TW", "numberOfListeners": 1411, "region": "TPE"}, {"city": "Singapore", "country": "SG", "numberOfListeners": 1216, "region": ""}, {"city": "Kuala Lumpur", "country": "MY", "numberOfListeners": 1215, "region": "14"}]}, "top_tracks_playcount": [5716436, 1564682, 2263105, 1661724, 90144, 608184, 175405, 1208460, 279216, 103675], "worldRank": 0},
    "2024-03-13": {"followers": 36955, "monthlyListeners": 72986, "topCities": {"items": [{"city": "Tokyo", "country": "JP", "numberOfListeners": 3544, "region": "13"}, {"city": "Jakarta", "country": "ID", "numberOfListeners": 1755, "region": "JK"}, {"city": "Taipei", "country": "TW", "numberOfListeners": 1430, "region": "TPE"}, {"city": "Singapore", "country": "SG", "numberOfListeners": 1231, "region": ""}, {"city": "Kuala Lumpur", "country": "MY", "numberOfListeners": 1208, "region": "14"}]}, "top_tracks_playcount": [5725700, 1570741, 2268258, 1664571, 92256, 609835, 176837, 1209317, 279907, 103798], "worldRank": 0},
    "2024-03-19": {"followers": 37090, "monthlyListeners": 73033, "topCities": {"items": [{"city": "Tokyo", "country": "JP", "numberOfListeners": 3680, "region": "13"}, {"city": "Jakarta", "country": "ID", "numberOfListeners": 1737, "region": "JK"}, {"city": "Taipei", "country": "TW", "numberOfListeners": 1454, "region": "TPE"}, {"city": "Singapore", "country": "SG", "numberOfListeners": 1238, "region": ""}, {"city": "Kuala Lumpur", "country": "MY", "numberOfListeners": 1165, "region": "14"}]}, "top_tracks_playcount": [5739944, 1581210, 2276817, 1669462, 96337, 612714, 179187, 1210586, 281002, 103999], "worldRank": 0},
    "2024-03-22": {"followers": 37165, "monthlyListeners": 72887, "topCities": {"items": [{"city": "Tokyo", "country": "JP", "numberOfListeners": 3688, "region": "13"}, {"city": "Jakarta", "country": "ID", "numberOfListeners": 1725, "region": "JK"}, {"city": "Taipei", "country": "TW", "numberOfListeners": 1485, "region": "TPE"}, {"city": "Singapore", "country": "SG", "numberOfListeners": 1239, "region": ""}, {"city": "Kuala Lumpur", "country": "MY", "numberOfListeners": 1149, "region": "14"}]}, "top_tracks_playcount": [5752141, 1589959, 2283990, 1673712, 100068, 615090, 181151, 1211774, 281921, 104128], "worldRank": 0},
    "2024-03-25": {"followers": 37221, "monthlyListeners": 72859, "topCities": {"items": [{"city": "Tokyo", "country": "JP", "numberOfListeners": 3663, "region": "13"}, {"city": "Jakarta", "country": "ID", "numberOfListeners": 1704, "region": "JK"}, {"city": "Taipei", "country": "TW", "numberOfListeners": 1480, "region": "TPE"}, {"city": "Singapore", "country": "SG", "numberOfListeners": 1229, "region": ""}, {"city": "Kuala Lumpur", "country": "MY", "numberOfListeners": 1147, "region": "14"}]}, "top_tracks_playcount": [5760653, 1595887, 2288751, 1676744, 102411, 616781, 182639, 1212499, 282587, 104294], "worldRank": 0},
    "2024-03-28": {"followers": 37301, "monthlyListeners": 73030, "topCities": {"items": [{"city": "Tokyo", "country": "JP", "numberOfListeners": 3730, "region": "13"}, {"city": "Jakarta", "country": "ID", "numberOfListeners": 1692, "region": "JK"}, {"city": "Taipei", "country": "TW", "numberOfListeners": 1486, "region": "TPE"}, {"city": "Singapore", "country": "SG", "numberOfListeners": 1230, "region": ""}, {"city": "Kuala Lumpur", "country": "MY", "numberOfListeners": 1161, "region": "14"}]}, "top_tracks_playcount": [5769871, 1602384, 2293782, 1679937, 105393, 618524, 184077, 1213342, 283263, 104405], "worldRank": 0},
    "2024-03-31": {"followers": 37378, "monthlyListeners": 72954, "topCities": {"items": [{"city": "Tokyo", "country": "JP", "numberOfListeners": 3779, "region": "13"}, {"city": "Jakarta", "country": "ID", "numberOfListeners": 1667, "region": "JK"}, {"city": "Taipei", "country": "TW", "numberOfListeners": 1485, "region": "TPE"}, {"city": "Singapore", "country": "SG", "numberOfListeners": 1228, "region": ""}, {"city": "Kuala Lumpur", "country": "MY", "numberOfListeners": 1151, "region": "14"}]}, "top_tracks_playcount": [5778343, 1608081, 2298573, 1682912, 108091, 620290, 185647, 1214054, 283885, 104508], "worldRank": 0},
    "2024-04-03": {"followers": 37450, "monthlyListeners": 72888, "topCities": {"items": [{"city": "Tokyo", "country": "JP", "numberOfListeners": 3830, "region": "13"}, {"city": "Jakarta", "country": "ID", "numberOfListeners": 1658, "region": "JK"}, {"city": "Taipei", "country": "TW", "numberOfListeners": 1497, "region": "TPE"}, {"city": "Singapore", "country": "SG", "numberOfListeners": 1232, "region": ""}, {"city": "Kuala Lumpur", "country": "MY", "numberOfListeners": 1145, "region": "14"}]}, "top_tracks_playcount": [5783902, 1611712, 2301721, 1684755, 109915, 621328, 186531, 1214502, 284271, 104578], "worldRank": 0},
    "2024-04-06": {"followers": 37518, "monthlyListeners": 72631, "topCities": {"items": [{"city": "Tokyo", "country": "JP", "numberOfListeners": 3882, "region": "13"}, {"city": "Jakarta", "country": "ID", "numberOfListeners": 1614, "region": "JK"}, {"city": "Taipei", "country": "TW", "numberOfListeners": 1451, "region": "TPE"}, {"city": "Singapore", "country": "SG", "numberOfListeners": 1213, "region": ""}, {"city": "Kuala Lumpur", "country": "MY", "numberOfListeners": 1117, "region": "14"}]}, "top_tracks_playcount": [5796879, 1620053, 2308418, 1688488, 113696, 623550, 188474, 1215565, 285135, 104734], "worldRank": 0},
    "2024-04-09": {"followers": 37584, "monthlyListeners": 72481, "topCities": {"items": [{"city": "Tokyo", "country": "JP", "numberOfListeners": 3891, "region": "13"}, {"city": "Jakarta", "country": "ID", "numberOfListeners": 1625, "region": "JK"}, {"city": "Taipei", "country": "TW", "numberOfListeners": 1412, "region": "TPE"}, {"city": "Singapore", "country": "SG", "numberOfListeners": 1220, "region": ""}, {"city": "Kuala Lumpur", "country": "MY", "numberOfListeners": 1116, "region": "14"}]}, "top_tracks_playcount": [5802486, 1623836, 2311413, 1690131, 115282, 624575, 189342, 1216134, 285573, 104787], "worldRank": 0},
    "2024-04-12": {"followers": 37653, "monthlyListeners": 72255, "topCities": {"items": [{"city": "Tokyo", "country": "JP", "numberOfListeners": 3842, "region": "13"}, {"city": "Jakarta", "country": "ID", "numberOfListeners": 1608, "region": "JK"}, {"city": "Taipei", "country": "TW", "numberOfListeners": 1392, "region": "TPE"}, {"city": "Singapore", "country": "SG", "numberOfListeners": 1203, "region": ""}, {"city": "Kuala Lumpur", "country": "MY", "numberOfListeners": 1111, "region": "14"}]}, "top_tracks_playcount": [5813691, 1631927, 2317897, 1693490, 118872, 626873, 191192, 1217340, 286431, 104900], "worldRank": 0},
    "2024-04-15": {"followers": 37692, "monthlyListeners": 71813, "topCities": {"items": [{"city": "Tokyo", "country": "JP", "numberOfListeners": 3733, "region": "13"}, {"city": "Jakarta", "country": "ID", "numberOfListeners": 1613, "region": "JK"}, {"city": "Taipei", "country": "TW", "numberOfListeners": 1376, "region": "TPE"}, {"city": "Singapore", "country": "SG", "numberOfListeners": 1204, "region": ""}, {"city": "Kuala Lumpur", "country": "MY", "numberOfListeners": 1146, "region": "14"}]}, "top_tracks_playcount": [5821608, 1637823, 2322736, 1695768, 121343, 628649, 192471, 1218050, 287042, 104982], "worldRank": 0},
    "2024-04-18": {"followers": 37747, "monthlyListeners": 71471, "topCities": {"items": [{"city": "Tokyo", "country": "JP", "numberOfListeners": 3742, "region": "13"}, {"city": "Jakarta", "country": "ID", "numberOfListeners": 1605, "region": "JK"}, {"city": "Taipei", "country": "TW", "numberOfListeners": 1369, "region": "TPE"}, {"city": "Singapore", "country": "SG", "numberOfListeners": 1211, "region": ""}, {"city": "Kuala Lumpur", "country": "MY", "numberOfListeners": 1163, "region": "14"}]}, "top_tracks_playcount": [5827338, 1642028, 2326002, 1697357, 123141, 629686, 193353, 1218552, 287428, 105049], "worldRank": 0},
    "2024-04-21": {"followers": 37817, "monthlyListeners": 70962, "topCities": {"items": [{"city": "Tokyo", "country": "JP", "numberOfListeners": 3745, "region": "13"}, {"city": "Jakarta", "country": "ID", "numberOfListeners": 1619, "region": "JK"}, {"city": "Taipei", "country": "TW", "numberOfListeners": 1361, "region": "TPE"}, {"city": "Singapore", "country": "SG", "numberOfListeners": 1204, "region": ""}, {"city": "Kuala Lumpur", "country": "MY", "numberOfListeners": 1173, "region": "14"}]}, "top_tracks_playcount": [5838719, 1650222, 2332394, 1700726, 126497, 631718, 195052, 1219533, 288239, 105202], "worldRank": 0},
    "2024-04-24": {"followers": 37881, "monthlyListeners": 70560, "topCities": {"items": [{"city": "Tokyo", "country": "JP", "numberOfListeners": 3708, "region": "13"}, {"city": "Jakarta", "country": "ID", "numberOfListeners": 1629, "region": "JK"}, {"city": "Taipei", "country": "TW", "numberOfListeners": 1341, "region": "TPE"}, {"city": "Singapore", "country": "SG", "numberOfListeners": 1190, "region": ""}, {"city": "Kuala Lumpur", "country": "MY", "numberOfListeners": 1160, "region": "14"}]}, "top_tracks_playcount": [5847013, 1656047, 2337299, 1703311, 128911, 633264, 196333, 1220397, 288790, 105329], "worldRank": 0},
    "2024-04-27": {"followers": 37925, "monthlyListeners": 70168, "topCities": {"items": [{"city": "Tokyo", "country": "JP", "numberOfListeners": 3621, "region": "13"}, {"city": "Jakarta", "country": "ID", "numberOfListeners": 1642, "region": "JK"}, {"city": "Taipei", "country": "TW", "numberOfListeners": 1319, "region": "TPE"}, {"city": "Singapore", "country": "SG", "numberOfListeners": 1174, "region": ""}, {"city": "Kuala Lumpur", "country": "MY", "numberOfListeners": 1165, "region": "14"}]}, "top_tracks_playcount": [5855159, 1662031, 2342276, 1705818, 131598, 635007, 197808, 1221366, 289403, 105422], "worldRank": 0},
    "2024-04-30": {"followers": 37973, "monthlyListeners": 69632, "topCities": {"items": [{"city": "Tokyo", "country": "JP", "numberOfListeners": 3522, "region": "13"}, {"city": "Jakarta", "country": "ID", "numberOfListeners": 1649, "region": "JK"}, {"city": "Taipei", "country": "TW", "numberOfListeners": 1310, "region": "TPE"}, {"city": "Singapore", "country": "SG", "numberOfListeners": 1163, "region": ""}, {"city": "Kuala Lumpur", "country": "MY", "numberOfListeners": 1142, "region": "14"}]}, "top_tracks_playcount": [5863104, 1667589, 2347032, 1708192, 133945, 636697, 199162, 1222129, 289993, 105539], "worldRank": 0},
    "2024-05-03": {"followers": 38012, "monthlyListeners": 68856, "topCities": {"items": [{"city": "Tokyo", "country": "JP", "numberOfListeners": 3377, "region": "13"}, {"city": "Jakarta", "country": "ID", "numberOfListeners": 1647, "region": "JK"}, {"city": "Taipei", "country": "TW", "numberOfListeners": 1310, "region": "TPE"}, {"city": "Singapore", "country": "SG", "numberOfListeners": 1175, "region": ""}, {"city": "Kuala Lumpur", "country": "MY", "numberOfListeners": 1140, "region": "14"}]}, "top_tracks_playcount": [5871233, 1673408, 2352072, 1710596, 136335, 638216, 200472, 1222938, 290575, 105660], "worldRank": 0},
    "2024-05-10": {"followers": 38105, "monthlyListeners": 68271, "topCities": {"items": [{"city": "Tokyo", "country": "JP", "numberOfListeners": 3380, "region": "13"}, {"city": "Jakarta", "country": "ID", "numberOfListeners": 1682, "region": "JK"}, {"city": "Taipei", "country": "TW", "numberOfListeners": 1333, "region": "TPE"}, {"city": "Singapore", "country": "SG", "numberOfListeners": 1145, "region": ""}, {"city": "Kuala Lumpur", "country": "MY", "numberOfListeners": 1109, "region": "14"}]}, "top_tracks_playcount": [5887143, 1684390, 2361542, 1715352, 140799, 641400, 203227, 1224460, 291681, 105863], "worldRank": 0},
    "2024-05-12": {"followers": 38169, "monthlyListeners": 68059, "topCities": {"items": [{"city": "Tokyo", "country": "JP", "numberOfListeners": 3337, "region": "13"}, {"city": "Jakarta", "country": "ID", "numberOfListeners": 1676, "region": "JK"}, {"city": "Taipei", "country": "TW", "numberOfListeners": 1349, "region": "TPE"}, {"city": "Singapore", "country": "SG", "numberOfListeners": 1132, "region": ""}, {"city": "Kuala Lumpur", "country": "MY", "numberOfListeners": 1112, "region": "14"}]}, "top_tracks_playcount": [5894856, 1689975, 2366259, 1717642, 143037, 642839, 204563, 1225186, 292240, 105954], "worldRank": 0},
    "2024-05-15": {"followers": 38224, "monthlyListeners": 68266, "topCities": {"items": [{"city": "Tokyo", "country": "JP", "numberOfListeners": 3217, "region": "13"}, {"city": "Jakarta", "country": "ID", "numberOfListeners": 1710, "region": "JK"}, {"city": "Taipei", "country": "TW", "numberOfListeners": 1357, "region": "TPE"}, {"city": "Singapore", "country": "SG", "numberOfListeners": 1142, "region": ""}, {"city": "Kuala Lumpur", "country": "MY", "numberOfListeners": 1090, "region": "14"}]}, "top_tracks_playcount": [5903131, 1695678, 2371211, 1719927, 145442, 644272, 205899, 1225950, 292861, 106053], "worldRank": 0},
    "2024-05-18": {"followers": 38272, "monthlyListeners": 68217, "topCities": {"items": [{"city": "Tokyo", "country": "JP", "numberOfListeners": 3103, "region": "13"}, {"city": "Jakarta", "country": "ID", "numberOfListeners": 1711, "region": "JK"}, {"city": "Taipei", "country": "TW", "numberOfListeners": 1370, "region": "TPE"}, {"city": "Singapore", "country": "SG", "numberOfListeners": 1137, "region": ""}, {"city": "Kuala Lumpur", "country": "MY", "numberOfListeners": 1067, "region": "14"}]}, "top_tracks_playcount": [5911009, 1701473, 2376478, 1722361, 147966, 645772, 207260, 1226753, 293538, 106171], "worldRank": 0},
    "2024-05-21": {"followers": 38389, "monthlyListeners": 68100, "topCities": {"items": [{"city": "Tokyo", "country": "JP", "numberOfListeners": 3078, "region": "13"}, {"city": "Jakarta", "country": "ID", "numberOfListeners": 1704, "region": "JK"}, {"city": "Taipei", "country": "TW", "numberOfListeners": 1331, "region": "TPE"}, {"city": "Singapore", "country": "SG", "numberOfListeners": 1130, "region": ""}, {"city": "Kuala Lumpur", "country": "MY", "numberOfListeners": 1055, "region": "14"}]}, "top_tracks_playcount": [5918812, 1706969, 2381163, 1724830, 150006, 647328, 208559, 1227517, 294107, 106269], "worldRank": 0},
    "2024-05-27": {"followers": 38810, "monthlyListeners": 70070, "topCities": {"items": [{"city": "Tokyo", "country": "JP", "numberOfListeners": 3196, "region": "13"}, {"city": "Jakarta", "country": "ID", "numberOfListeners": 1732, "region": "JK"}, {"city": "Taipei", "country": "TW", "numberOfListeners": 1321, "region": "TPE"}, {"city": "Singapore", "country": "SG", "numberOfListeners": 1196, "region": ""}, {"city": "Kuala Lumpur", "country": "MY", "numberOfListeners": 1073, "region": "14"}]}, "top_tracks_playcount": [5935893, 1718770, 46896, 2390612, 1729838, 154261, 650601, 211474, 1228988, 295227], "worldRank": 0},
    "2024-05-30": {"followers": 38911, "monthlyListeners": 71086, "topCities": {"items": [{"city": "Tokyo", "country": "JP", "numberOfListeners": 3251, "region": "13"}, {"city": "Jakarta", "country": "ID", "numberOfListeners": 1771, "region": "JK"}, {"city": "Taipei", "country": "TW", "numberOfListeners": 1366, "region": "TPE"}, {"city": "Singapore", "country": "SG", "numberOfListeners": 1231, "region": ""}, {"city": "Kuala Lumpur", "country": "MY", "numberOfListeners": 1085, "region": "14"}]}, "top_tracks_playcount": [5944221, 68073, 1725054, 2395602, 1732308, 156366, 652149, 212851, 1229736, 295815], "worldRank": 0},
    "2024-06-02": {"followers": 38991, "monthlyListeners": 71740, "topCities": {"items": [{"city": "Tokyo", "country": "JP", "numberOfListeners": 3247, "region": "13"}, {"city": "Jakarta", "country": "ID", "numberOfListeners": 1804, "region": "JK"}, {"city": "Taipei", "country": "TW", "numberOfListeners": 1371, "region": "TPE"}, {"city": "Singapore", "country": "SG", "numberOfListeners": 1264, "region": ""}, {"city": "Kuala Lumpur", "country": "MY", "numberOfListeners": 1102, "region": "14"}]}, "top_tracks_playcount": [85712, 5952183, 1730644, 2400154, 1734896, 158487, 653682, 214068, 1230504, 296394], "worldRank": 0}
  }
}