{
  "branch": null,
  "generation": null,
  "id": "5NkXryxdtHg2t0ZcXfzeyq",
  "name": "hololive Indonesia 1st Generation",
  "stats": {
    "2023-09-04": {"monthlyListeners": 12382},
    "2023-10-04": {"monthlyListeners": 11908},
    "2023-11-05": {"monthlyListeners": 11051},
    "2023-12-04": {"monthlyListeners": 11264},
    "2024-01-06": {"followers": 4830, "monthlyListeners": 12177, "topCities": {"items": [{"city": "Jakarta", "country": "ID", "numberOfListeners": 2097, "region": "JK"}, {"city": "Bandung", "country": "ID", "numberOfListeners": 829, "region": "JB"}, {"city": "Surabaya", "country": "ID", "numberOfListeners": 718, "region": "JI"}, {"city": "Semarang", "country": "ID", "numberOfListeners": 543, "region": "JT"}, {"city": "Bekasi", "country": "ID", "numberOfListeners": 401, "region": "JB"}]}, "worldRank": 0},
    "2024-01-07": {"followers": 4867, "monthlyListeners": 12276, "topCities": {"items": [{"city": "Jakarta", "country": "ID", "numberOfListeners": 2105, "region": "JK"}, {"city": "Bandung", "country": "ID", "numberOfListeners": 838, "region": "JB"}, {"city": "Surabaya", "country": "ID", "numberOfListeners": 723, "region": "JI"}, {"city": "Semarang", "country": "ID", "numberOfListeners": 546, "region": "JT"}, {"city": "Bekasi", "country": "ID", "numberOfListeners": 402, "region": "JB"}]}, "worldRank": 0},
    "2024-01-10": {"followers": 4963, "monthlyListeners": 12427, "topCities": {"items": [{"city": "Jakarta", "country": "ID", "numberOfListeners": 2126, "region": "JK"}, {"city": "Bandung", "country": "ID", "numberOfListeners": 836, "region": "JB"}, {"city": "Surabaya", "country": "ID", "numberOfListeners": 727, "region": "JI"}, {"city": "Semarang", "country": "ID", "numberOfListeners": 557, "region": "JT"}, {"city": "Bekasi", "country": "ID", "numberOfListeners": 400, "region": "JB"}]}, "worldRank": 0},
    "2024-01-17": {"followers": 5186, "monthlyListeners": 12335, "topCities": {"items": [{"city": "Jakarta", "country": "ID", "numberOfListeners": 2103, "region": "JK"}, {"city": "Bandung", "country": "ID", "numberOfListeners": 823, "region": "JB"}, {"city": "Surabaya", "country": "ID", "numberOfListeners": 693, "region": "JI"}, {"city": "Semarang", "country": "ID", "numberOfListeners": 525, "region": "JT"}, {"city": "Bekasi", "country": "ID", "numberOfListeners": 391, "region": "JB"}]}, "worldRank": 0},
    "2024-01-19": {"followers": 5267, "monthlyListeners": 12078, "topCities": {"items": [{"city": "Jakarta", "country": "ID", "numberOfListeners": 2029, "region": "JK"}, {"city": "Bandung", "country": "ID", "numberOfListeners": 813, "region": "JB"}, {"city": "Surabaya", "country": "ID", "numberOfListeners": 667, "region": "JI"}, {"city": "Semarang", "country": "ID", "numberOfListeners": 512, "region": "JT"}, {"city": "Bekasi", "country": "ID", "numberOfListeners": 374, "region": "JB"}]}, "worldRank": 0},
    "2024-01-21": {"followers": 5324, "monthlyListeners": 11961, "topCities": {"items": [{"city": "Jakarta", "country": "ID", "numberOfListeners": 2010, "region": "JK"}, {"city": "Bandung", "country": "ID", "numberOfListeners": 795, "region": "JB"}, {"city": "Surabaya", "country": "ID", "numberOfListeners": 648, "region": "JI"}, {"city": "Semarang", "country": "ID", "numberOfListeners": 495, "region": "JT"}, {"city": "Tokyo", "country": "JP", "numberOfListeners": 381, "region": "13"}]}, "top_tracks_playcount": [526100, 311181, 13972], "worldRank": 0},
    "2024-01-22": {"followers": 5377, "monthlyListeners": 11955, "topCities": {"items": [{"city": "Jakarta", "country": "ID", "numberOfListeners": 2020, "region": "JK"}, {"city": "Bandung", "country": "ID", "numberOfListeners": 790, "region": "JB"}, {"city": "Surabaya", "country": "ID", "numberOfListeners": 651, "region": "JI"}, {"city": "Semarang", "country": "ID", "numberOfListeners": 503, "region": "JT"}, {"city": "Tokyo", "country": "JP", "numberOfListeners": 379, "region": "13"}]}, "top_tracks_playcount": [526914, 311505, 13984], "worldRank": 0},
    "2024-01-25": {"followers": 5447, "monthlyListeners": 11839, "topCities": {"items": [{"city": "Jakarta", "country": "ID", "numberOfListeners": 2006, "region": "JK"}, {"city": "Bandung", "country": "ID", "numberOfListeners": 774, "region": "JB"}, {"city": "Surabaya", "country": "ID", "numberOfListeners": 624, "region": "JI"}, {"city": "Semarang", "country": "ID", "numberOfListeners": 475, "region": "JT"}, {"city": "Tokyo", "country": "JP", "numberOfListeners": 385, "region": "13"}]}, "top_tracks_playcount": [529098, 312586, 14027], "worldRank": 0},
    "2024-01-28": {"followers": 5553, "monthlyListeners": 11705, "topCities": {"items": [{"city": "Jakarta", "country": "ID", "numberOfListeners": 2004, "region": "JK"}, {"city": "Bandung", "country": "ID", "numberOfListeners": 731, "region": "JB"}, {"city": "Surabaya", "country": "ID", "numberOfListeners": 615, "region": "JI"}, {"city": "Semarang", "country": "ID", "numberOfListeners": 467, "region": "JT"}, {"city": "Tokyo", "country": "JP", "numberOfListeners": 393, "region": "13"}]}, "top_tracks_playcount": [531174, 313609, 14060], "worldRank": 0},
    "2024-01-31": {"followers": 5618, "monthlyListeners": 11657, "topCities": {"items": [{"city": "Jakarta", "country": "ID", "numberOfListeners": 2002, "region": "JK"}, {"city": "Bandung", "country": "ID", "numberOfListeners": 722, "region": "JB"}, {"city": "Surabaya", "country": "ID", "numberOfListeners": 612, "region": "JI"}, {"city": "Semarang", "country": "ID", "numberOfListeners": 451, "region": "JT"}, {"city": "Tokyo", "country": "JP", "numberOfListeners": 393, "region": "13"}]}, "top_tracks_playcount": [533302, 314586, 14101], "worldRank": 0},
    "2024-02-03": {"followers": 5734, "monthlyListeners": 11500, "topCities": {"items": [{"city": "Jakarta", "country": "ID", "numberOfListeners": 1978, "region": "JK"}, {"city": "Bandung", "country": "ID", "numberOfListeners": 721, "region": "JB"}, {"city": "Surabaya", "country": "ID", "numberOfListeners": 587, "region": "JI"}, {"city": "Semarang", "country": "ID", "numberOfListeners": 453, "region": "JT"}, {"city": "Tokyo", "country": "JP", "numberOfListeners": 393, "region": "13"}]}, "top_tracks_playcount": [535371, 315626, 14136], "worldRank": 0},
    "2024-02-06": {"followers": 5838, "monthlyListeners": 11187, "topCities": {"items": [{"city": "Jakarta", "country": "ID", "numberOfListeners": 1931, "region": "JK"}, {"city": "Bandung", "country": "ID", "numberOfListeners": 698, "region": "JB"}, {"city": "Surabaya", "country": "ID", "numberOfListeners": 568, "region": "JI"}, {"city": "Semarang", "country": "ID", "numberOfListeners": 436, "region": "JT"}, {"city": "Tokyo", "country": "JP", "numberOfListeners": 395, "region": "13"}]}, "top_tracks_playcount": [537477, 316621, 14174], "worldRank": 0},
    "2024-02-09": {"followers": 5949, "monthlyListeners": 11032, "topCities": {"items": [{"city": "Jakarta", "country": "ID", "numberOfListeners": 1914, "region": "JK"}, {"city": "Bandung", "country": "ID", "numberOfListeners": 666, "region": "JB"}, {"city": "Surabaya", "country": "ID", "numberOfListeners": 538, "region": "JI"}, {"city": "Semarang", "country": "ID", "numberOfListeners": 452, "region": "JT"}, {"city": "Tokyo", "country": "JP", "numberOfListeners": 369, "region": "13"}]}, "top_tracks_playcount": [539568, 317605, 14227], "worldRank": 0},
    "2024-02-12": {"followers": 6103, "monthlyListeners": 10924, "topCities": {"items": [{"city": "Jakarta", "country": "ID", "numberOfListeners": 1871, "region": "JK"}, {"city": "Bandung", "country": "ID", "numberOfListeners": 680, "region": "JB"}, {"city": "Surabaya", "country": "ID", "numberOfListeners": 524, "region": "JI"}, {"city": "Semarang", "country": "ID", "numberOfListeners": 462, "region": "JT"}, {"city": "Tokyo", "country": "JP", "numberOfListeners": 389, "region": "13"}]}, "top_tracks_playcount": [541587, 318592, 14270], "worldRank": 0},
    "2024-02-15": {"followers": 6214, "monthlyListeners": 10774, "topCities": {"items": [{"city": "Jakarta", "country": "ID", "numberOfListeners": 1865, "region": "JK"}, {"city": "Bandung", "country": "ID", "numberOfListeners": 684, "region": "JB"}, {"city": "Surabaya", "country": "ID", "numberOfListeners": 522, "region": "JI"}, {"city": "Semarang", "country": "ID", "numberOfListeners": 458, "region": "JT"}, {"city": "Tokyo", "country": "JP", "numberOfListeners": 381, "region": "13"}]}, "top_tracks_playcount": [543575, 319541, 14302], "worldRank": 0}
  }
}